ubkisaas/__init__.py
ubkisaas/ubki_report.py
ubkisaas/ubki_request.py
ubkisaas-1.1.dist-info/LICENSE
ubkisaas-1.1.dist-info/METADATA
ubkisaas-1.1.dist-info/WHEEL
ubkisaas-1.1.dist-info/top_level.txt
ubkisaas-1.1.dist-info/RECORD
