Metadata-Version: 2.1
Name: ubkisaas
Version: 1.1
Summary: library for receiving UBKI data from the official website and parsing them and getting features for scoring analysis
Home-page: https://github.com/Asirg/ubkisaas
Author: Asir Muminov
Author-email: vojt.tieg295i@gmail.com
License: UNKNOWN
Platform: UNKNOWN
Classifier: Programming Language :: Python :: 3
Classifier: License :: OSI Approved :: MIT License
Classifier: Operating System :: OS Independent
Requires-Python: >=3.6
License-File: LICENSE
Requires-Dist: requests
Requires-Dist: python-dotenv
